exctrap/__init__.py
exctrap/py.typed
exctrap-0.2.dist-info/LICENSE
exctrap-0.2.dist-info/METADATA
exctrap-0.2.dist-info/WHEEL
exctrap-0.2.dist-info/top_level.txt
exctrap-0.2.dist-info/RECORD
