Metadata-Version: 2.1
Name: exctrap
Version: 0.2
Summary: Exception trap
Home-page: https://github.com/isaacto/exctrap
Author: Isaac To
Author-email: isaac.to@gmail.com
Classifier: Development Status :: 4 - Beta
Classifier: Programming Language :: Python :: 3.7
Classifier: Programming Language :: Python :: 3.8
Classifier: Programming Language :: Python :: 3.9
Classifier: Programming Language :: Python :: 3.10
Classifier: Topic :: Software Development :: Libraries
Classifier: License :: OSI Approved :: MIT License
Classifier: Operating System :: OS Independent
Requires-Python: ~=3.7
License-File: LICENSE
